reflex_nova/__init__.py
reflex_nova/nova.py
reflex_nova/components/__init__.py
reflex_nova/components/model/__init__.py
reflex_nova/components/model/fields.py
reflex_nova/components/model/modules.py
reflex_nova/components/model/nomenclature.py
reflex_nova/components/model/sigfig.py
reflex_nova/components/model/units.py
reflex_nova/components/model/variables.py
reflex_nova/components/reflex/__init__.py
reflex_nova/components/reflex/components.py
reflex_nova/components/reflex/variables.py
reflex_nova/how_to/__init__.py
reflex_nova/modeling/__init__.py
reflex_nova/modeling/_old.py
reflex_nova/modeling/custom_parser.py
reflex_nova/modeling/parsing.py
reflex_nova/modeling/topological_model.py
reflex_nova/models/__init__.py
reflex_nova/models/asme/__init__.py
reflex_nova/models/asme/b31_3.py
reflex_nova/models/cycling/__init__.py
reflex_nova/models/cycling/frontal_area.py
reflex_nova/models/cycling/power_speed.py
reflex_nova/models/mechanics/__init__.py
reflex_nova/models/mechanics/materials/__init__.py
reflex_nova/models/mechanics/materials/flat_plates.py
reflex_nova/models/mechanics/statics/__init__.py
reflex_nova/models/mechanics/statics/body.py
reflex_nova/models/mechanics/statics/force.py
reflex_nova/models/mechanics/statics/node.py
reflex_nova/models/mechanics/statics/vector_solver.py
reflex_nova/models/mechanics/statics/vector_solver_test.py
reflex_nova/practice_problems/__init__.py
reflex_nova/primatives/__init__.py
reflex_nova/primatives/affine_transf.py
reflex_nova/primatives/affine_transforms.py
reflex_nova/primatives/axes.py
reflex_nova/primatives/axis.py
reflex_nova/primatives/circle.py
reflex_nova/primatives/circles.py
reflex_nova/primatives/force.py
reflex_nova/primatives/geometric.py
reflex_nova/primatives/interpolation.py
reflex_nova/primatives/line.py
reflex_nova/primatives/nums.py
reflex_nova/primatives/open_interval.py
reflex_nova/primatives/physical.py
reflex_nova/primatives/point.py
reflex_nova/primatives/polygon.py
reflex_nova-0.0.2.dist-info/METADATA
reflex_nova-0.0.2.dist-info/WHEEL
reflex_nova-0.0.2.dist-info/top_level.txt
reflex_nova-0.0.2.dist-info/RECORD
