Metadata-Version: 2.4
Name: reflex-nova
Version: 0.0.2
Summary: Reflex custom component nova
Author-email: Tyler <tn3wman@icloud.com>
License: Apache-2.0
Keywords: reflex,reflex-custom-components
Classifier: Development Status :: 4 - Beta
Requires-Python: >=3.10
Requires-Dist: reflex>=0.7.5
Requires-Dist: numpy>=2.2.3
Requires-Dist: sympy>=1.13.3
Requires-Dist: pint>=0.24.4
Requires-Dist: dill>=0.3.9
Requires-Dist: sortedcontainers>=2.4.0
Requires-Dist: reflex-mathjax>=0.0.1
Requires-Dist: reflex-mafs>=0.0.1
Provides-Extra: dev
Requires-Dist: build; extra == "dev"
Requires-Dist: twine; extra == "dev"
